luckytools/__init__.py
luckytools-0.71.dist-info/METADATA
luckytools-0.71.dist-info/WHEEL
luckytools-0.71.dist-info/top_level.txt
luckytools-0.71.dist-info/RECORD
