Metadata-Version: 2.4
Name: luckytools
Version: 0.71
Summary: Print utility
Author-email: sayginaego.say@gmail.com
Dynamic: author-email
Dynamic: summary
